fastquant/__init__.py
fastquant/config.py
fastquant/network.py
fastquant/notification.py
fastquant/portfolio.py
fastquant/backtest/__init__.py
fastquant/backtest/backtest.py
fastquant/backtest/backtest_indicators.py
fastquant/backtest/data_prep.py
fastquant/backtest/post_backtest.py
fastquant/data/JFC_1-1-2020_4-1-2020.csv
fastquant/data/JFC_2010-01-01_2019-01-01_OHLCV.csv
fastquant/data/JFC_20180101_20190110_DCV.csv
fastquant/data/JFC_disclosures_1-1-2020_5-1-2020.csv
fastquant/data/__init__.py
fastquant/data/bluechips.txt
fastquant/data/bt_sentiments_tests.pkl
fastquant/data/merged_stock_data.zip
fastquant/data/network.jpg
fastquant/data/senti_disclosures.pkl
fastquant/data/stock_table.csv
fastquant/data/stocklist.txt
fastquant/data/crypto/__init__.py
fastquant/data/crypto/crypto.py
fastquant/data/stocks/__init__.py
fastquant/data/stocks/phisix.py
fastquant/data/stocks/pse.py
fastquant/data/stocks/stocks.py
fastquant/data/stocks/yahoofinance.py
fastquant/data/web/__init__.py
fastquant/data/web/businesstimes.py
fastquant/data/web/twitter.py
fastquant/disclosures/__init__.py
fastquant/disclosures/base.py
fastquant/disclosures/investagrams.py
fastquant/disclosures/pse.py
fastquant/disclosures/sentiment.py
fastquant/indicators/__init__.py
fastquant/indicators/backtrader_indicators.py
fastquant/indicators/custom.py
fastquant/indicators/sentiment.py
fastquant/strategies/__init__.py
fastquant/strategies/base.py
fastquant/strategies/bollinger_band.py
fastquant/strategies/buy_and_hold.py
fastquant/strategies/custom.py
fastquant/strategies/ma_crossover.py
fastquant/strategies/macd.py
fastquant/strategies/mappings.py
fastquant/strategies/rsi.py
fastquant/strategies/sentiment.py
fastquant/utils/__init__.py
fastquant/utils/data_split.py
fastquant-0.1.8.1.data/scripts/get_disclosures
fastquant-0.1.8.1.data/scripts/update_cache
fastquant-0.1.8.1.dist-info/LICENSE
fastquant-0.1.8.1.dist-info/METADATA
fastquant-0.1.8.1.dist-info/WHEEL
fastquant-0.1.8.1.dist-info/top_level.txt
fastquant-0.1.8.1.dist-info/RECORD
