Metadata-Version: 2.1
Name: fastquant
Version: 0.1.8.1
Summary: Bringing data driven investments to the mainstream
Home-page: https://github.com/enzoampil/fastquant
Author: Lorenzo Ampil
Author-email: lorenzo.ampil@gmail.com
Classifier: Programming Language :: Python :: 3
Classifier: License :: OSI Approved :: GNU General Public License v3 (GPLv3)
Classifier: Operating System :: OS Independent
License-File: LICENSE
Requires-Dist: backtrader (>=1.9.75.123)
Requires-Dist: beautifulsoup4 (>=4.8.2)
Requires-Dist: black (>=19.10b0)
Requires-Dist: bs4 (>=0.0.1)
Requires-Dist: ccxt (>=1.31.1)
Requires-Dist: certifi (>=2019.11.28)
Requires-Dist: chardet (>=3.0.4)
Requires-Dist: croniter (>=0.3.35)
Requires-Dist: idna (>=2.8)
Requires-Dist: lxml (>=4.6.2)
Requires-Dist: matplotlib (>=3.2.2)
Requires-Dist: networkx (>=2.4)
Requires-Dist: numpy (>=1.18.0)
Requires-Dist: oauthlib (>=3.1.0)
Requires-Dist: pandas (>=1.1.5)
Requires-Dist: PySocks (>=1.7.1)
Requires-Dist: python-dateutil (>=2.8.1)
Requires-Dist: pytz (>=2019.3)
Requires-Dist: requests (>=2.22.0)
Requires-Dist: requests-oauthlib (>=1.3.0)
Requires-Dist: six (>=1.13.0)
Requires-Dist: soupsieve (>=1.9.5)
Requires-Dist: tqdm (>=4.28.1)
Requires-Dist: tweepy (>=3.8.0)
Requires-Dist: urllib3 (>=1.25.7)
Requires-Dist: yfinance (>=0.1.54)
Requires-Dist: nltk (>=3.5)
Requires-Dist: pre-commit
Requires-Dist: scipy
